mcp_server.py
iflow_mcp_organicmoron_sp_mcp-1.0.1.dist-info/licenses/LICENSE.txt
iflow_mcp_organicmoron_sp_mcp-1.0.1.dist-info/METADATA
iflow_mcp_organicmoron_sp_mcp-1.0.1.dist-info/WHEEL
iflow_mcp_organicmoron_sp_mcp-1.0.1.dist-info/entry_points.txt
iflow_mcp_organicmoron_sp_mcp-1.0.1.dist-info/top_level.txt
iflow_mcp_organicmoron_sp_mcp-1.0.1.dist-info/RECORD
