Metadata-Version: 2.4
Name: iflow-mcp_organicmoron_sp-mcp
Version: 1.0.1
Summary: Bridge between Super Productivity and MCP (Model Context Protocol) servers for Claude Desktop integration
Author: organicmoron
Requires-Python: >=3.8
License-File: LICENSE.txt
Requires-Dist: mcp>=1.0.0
Dynamic: author
Dynamic: description
Dynamic: description-content-type
Dynamic: license-file
Dynamic: requires-dist
Dynamic: requires-python
Dynamic: summary
